randomua/__init__.py
randomua/randomua.py
randomua-0.0.7.dist-info/METADATA
randomua-0.0.7.dist-info/WHEEL
randomua-0.0.7.dist-info/top_level.txt
randomua-0.0.7.dist-info/RECORD
